docutils_tinyhtml/__init__.py
docutils_tinyhtml/py.typed
docutils_tinyhtml/tiny-writer.css
docutils_tinyhtmlwriter-1.3.0.data/scripts/md2html-tiny
docutils_tinyhtmlwriter-1.3.0.data/scripts/rst2html-tiny
docutils_tinyhtmlwriter-1.3.0.dist-info/COPYING
docutils_tinyhtmlwriter-1.3.0.dist-info/METADATA
docutils_tinyhtmlwriter-1.3.0.dist-info/WHEEL
docutils_tinyhtmlwriter-1.3.0.dist-info/top_level.txt
docutils_tinyhtmlwriter-1.3.0.dist-info/RECORD
