Metadata-Version: 2.1
Name: docutils-tinyhtmlwriter
Version: 1.3.0
Summary: Docutils Writer producing Tiny HTML
Home-page: https://github.com/ondratu/docutils-tinyhtmlwriter
Author: Ondřej Tůma (McBig)
Author-email: mcbig@zeropage.cz
License: BSD
Platform: UNKNOWN
Classifier: Development Status :: 5 - Production/Stable
Classifier: Environment :: Console
Classifier: Intended Audience :: Developers
Classifier: Intended Audience :: End Users/Desktop
Classifier: License :: OSI Approved :: BSD License
Classifier: Natural Language :: English
Classifier: Natural Language :: Czech
Classifier: Operating System :: OS Independent
Classifier: Programming Language :: Python :: 3
Classifier: Topic :: Documentation
Classifier: Topic :: Software Development :: Documentation
Classifier: Topic :: Text Processing
Classifier: Topic :: Text Processing :: Markup
Classifier: Topic :: Utilities
Requires: docutils (>= 0.12)
Requires-Dist: docutils (>=0.12)
